Metadata-Version: 2.1
Name: face_live_detect_sdk
Version: 0.1.1
Summary: A Python SDK for liveness detection using a pre-trained model.
Home-page: https://github.com/gayathri-kannanv/liveness-detection-sdk
Author: rapiddata
Author-email: datascience.rapiddata@gmail.com
Classifier: Programming Language :: Python :: 3
Classifier: License :: OSI Approved :: MIT License
Classifier: Operating System :: OS Independent
Requires-Python: >=3.6
Requires-Dist: tensorflow
Requires-Dist: opencv-python-headless
Requires-Dist: flask
Requires-Dist: flask-cors
Requires-Dist: imutils
Requires-Dist: numpy
